{
  "Routes": [
    {
      "DownstreamPathTemplate": "/Upload-Documents",
      "DownstreamScheme": "https",
      "DownstreamHostAndPorts": [
        {
          "Host": "localhost",
          "Port": 7001
        }
      ],
      "UpstreamPathTemplate": "/api/Upload-Documents",
      "UpstreamHttpMethod": [ "POST" ],
      "QoSOptions": {
        "ExceptionsAllowedBeforeBreaking": 3,
        "DurationOfBreak": 1000,
        "TimeoutValue": 5000
      },
      "RetryPolicy": {
        "RetryCount": 3,
        "RetryBackOff": 1000
      },
      "AuthenticationOptions": { "AuthenticationProviderKey": "Bearer" }
    },
    {
      "DownstreamPathTemplate": "/Download-Document/{docId}",
      "DownstreamScheme": "https",
      "DownstreamHostAndPorts": [
        {
          "Host": "localhost",
          "Port": 7001
        }
      ],
      "UpstreamPathTemplate": "/api/Download-Document/{docId}",
      "UpstreamHttpMethod": [ "GET" ],
      "QoSOptions": {
        "ExceptionsAllowedBeforeBreaking": 3,
        "DurationOfBreak": 1000,
        "TimeoutValue": 5000
      },
      "RetryPolicy": {
        "RetryCount": 3,
        "RetryBackOff": 1000
      },
      "AuthenticationOptions": { "AuthenticationProviderKey": "Bearer" }
    },
    {
      "DownstreamPathTemplate": "/DocumentsListById/{caseId}",
      "DownstreamScheme": "https",
      "DownstreamHostAndPorts": [
        {
          "Host": "localhost",
          "Port": 7001
        }
      ],
      "UpstreamPathTemplate": "/api/DocumentsListById/{caseId}",
      "UpstreamHttpMethod": [ "GET" ],
      "QoSOptions": {
        "ExceptionsAllowedBeforeBreaking": 3,
        "DurationOfBreak": 1000,
        "TimeoutValue": 5000
      },
      "RetryPolicy": {
        "RetryCount": 3,
        "RetryBackOff": 1000
      },
      "AuthenticationOptions": { "AuthenticationProviderKey": "Bearer" }
    },
    {
      "DownstreamPathTemplate": "/download-all-documents/{caseId}",
      "DownstreamScheme": "https",
      "DownstreamHostAndPorts": [
        {
          "Host": "localhost",
          "Port": 7001
        }
      ],
      "UpstreamPathTemplate": "/api/download-all-documents/{caseId}",
      "UpstreamHttpMethod": [ "GET" ],
      "QoSOptions": {
        "ExceptionsAllowedBeforeBreaking": 3,
        "DurationOfBreak": 1000,
        "TimeoutValue": 5000
      },
      "RetryPolicy": {
        "RetryCount": 3,
        "RetryBackOff": 1000
      },
      "AuthenticationOptions": { "AuthenticationProviderKey": "Bearer" }
    },
    {
      "DownstreamPathTemplate": "/StoreDocuments",
      "DownstreamScheme": "https",
      "DownstreamHostAndPorts": [
        {
          "Host": "localhost",
          "Port": 7001
        }
      ],
      "UpstreamPathTemplate": "/api/StoreDocuments",
      "UpstreamHttpMethod": [ "POST" ],
      "QoSOptions": {
        "ExceptionsAllowedBeforeBreaking": 3,
        "DurationOfBreak": 1000,
        "TimeoutValue": 5000
      },
      "RetryPolicy": {
        "RetryCount": 3,
        "RetryBackOff": 1000
      },
      "AuthenticationOptions": { "AuthenticationProviderKey": "Bearer" }
    },
    {
      "DownstreamPathTemplate": "/FraudCaseRequest",
      "DownstreamScheme": "https",
      "DownstreamHostAndPorts": [
        {
          "Host": "localhost",
          "Port": 7001
        }
      ],
      "UpstreamPathTemplate": "/api/FraudCaseRequest",
      "UpstreamHttpMethod": [ "POST" ],
      "QoSOptions": {
        "ExceptionsAllowedBeforeBreaking": 3,
        "DurationOfBreak": 1000,
        "TimeoutValue": 5000
      },
      "RetryPolicy": {
        "RetryCount": 3,
        "RetryBackOff": 1000
      },
      "AuthenticationOptions": { "AuthenticationProviderKey": "Bearer" }
    },
    {
      "DownstreamPathTemplate": "/PerformCaseActions",
      "DownstreamScheme": "https",
      "DownstreamHostAndPorts": [
        {
          "Host": "localhost",
          "Port": 7001
        }
      ],
      "UpstreamPathTemplate": "/api/PerformCaseActions",
      "UpstreamHttpMethod": [ "POST" ],
      "QoSOptions": {
        "ExceptionsAllowedBeforeBreaking": 3,
        "DurationOfBreak": 1000,
        "TimeoutValue": 5000
      },
      "RetryPolicy": {
        "RetryCount": 3,
        "RetryBackOff": 1000
      },
      "AuthenticationOptions": { "AuthenticationProviderKey": "Bearer" }
    },
    {
      "DownstreamPathTemplate": "/InvestigationList/{userId}",
      "DownstreamScheme": "https",
      "DownstreamHostAndPorts": [
        {
          "Host": "localhost",
          "Port": 7001
        }
      ],
      "UpstreamPathTemplate": "/api/InvestigationList/{userId}",
      "UpstreamHttpMethod": [ "GET" ],
      "QoSOptions": {
        "ExceptionsAllowedBeforeBreaking": 3,
        "DurationOfBreak": 1000,
        "TimeoutValue": 5000
      },
      "RetryPolicy": {
        "RetryCount": 3,
        "RetryBackOff": 1000
      },
      "AuthenticationOptions": { "AuthenticationProviderKey": "Bearer" }
    },
    {
      "DownstreamPathTemplate": "/GetCaseData/{caseId}",
      "DownstreamScheme": "https",
      "DownstreamHostAndPorts": [
        {
          "Host": "localhost",
          "Port": 7001
        }
      ],
      "UpstreamPathTemplate": "/api/GetCaseData/{caseId}",
      "UpstreamHttpMethod": [ "GET" ],
      "QoSOptions": {
        "ExceptionsAllowedBeforeBreaking": 3,
        "DurationOfBreak": 1000,
        "TimeoutValue": 5000
      },
      "RetryPolicy": {
        "RetryCount": 3,
        "RetryBackOff": 1000
      },
      "AuthenticationOptions": { "AuthenticationProviderKey": "Bearer" }
    },
    {
      "DownstreamPathTemplate": "/CaseHistory/{caseId}",
      "DownstreamScheme": "https",
      "DownstreamHostAndPorts": [
        {
          "Host": "localhost",
          "Port": 7001
        }
      ],
      "UpstreamPathTemplate": "/api/CaseHistory/{caseId}",
      "UpstreamHttpMethod": [ "GET" ],
      "QoSOptions": {
        "ExceptionsAllowedBeforeBreaking": 3,
        "DurationOfBreak": 1000,
        "TimeoutValue": 5000
      },
      "RetryPolicy": {
        "RetryCount": 3,
        "RetryBackOff": 1000
      },
      "AuthenticationOptions": { "AuthenticationProviderKey": "Bearer" }
    },
    {
      "DownstreamPathTemplate": "/get-all-stateWiseManagers",
      "DownstreamScheme": "https",
      "DownstreamHostAndPorts": [
        {
          "Host": "localhost",
          "Port": 7001
        }
      ],
      "UpstreamPathTemplate": "/api/get-all-stateWiseManagers",
      "UpstreamHttpMethod": [ "GET" ],
      "QoSOptions": {
        "ExceptionsAllowedBeforeBreaking": 3,
        "DurationOfBreak": 1000,
        "TimeoutValue": 5000
      },
      "RetryPolicy": {
        "RetryCount": 3,
        "RetryBackOff": 1000
      },
      "AuthenticationOptions": { "AuthenticationProviderKey": "Bearer" }
    },
    {
      "DownstreamPathTemplate": "/get-all-vendors",
      "DownstreamScheme": "https",
      "DownstreamHostAndPorts": [
        {
          "Host": "localhost",
          "Port": 7001
        }
      ],
      "UpstreamPathTemplate": "/api/get-all-vendors",
      "UpstreamHttpMethod": [ "GET" ],
      "QoSOptions": {
        "ExceptionsAllowedBeforeBreaking": 3,
        "DurationOfBreak": 1000,
        "TimeoutValue": 5000
      },
      "RetryPolicy": {
        "RetryCount": 3,
        "RetryBackOff": 1000
      },
      "AuthenticationOptions": { "AuthenticationProviderKey": "Bearer" }
    },
    {
      "DownstreamPathTemplate": "/get-all-fieldInvestigator",
      "DownstreamScheme": "https",
      "DownstreamHostAndPorts": [
        {
          "Host": "localhost",
          "Port": 7001
        }
      ],
      "UpstreamPathTemplate": "/api/get-all-fieldInvestigator",
      "UpstreamHttpMethod": [ "GET" ],
      "QoSOptions": {
        "ExceptionsAllowedBeforeBreaking": 3,
        "DurationOfBreak": 1000,
        "TimeoutValue": 5000
      },
      "RetryPolicy": {
        "RetryCount": 3,
        "RetryBackOff": 1000
      },
      "AuthenticationOptions": { "AuthenticationProviderKey": "Bearer" }
    },
    {
      "DownstreamPathTemplate": "/get-users/{userRoleId}",
      "DownstreamScheme": "https",
      "DownstreamHostAndPorts": [
        {
          "Host": "localhost",
          "Port": 7001
        }
      ],
      "UpstreamPathTemplate": "/api/get-users/{userRoleId}",
      "UpstreamHttpMethod": [ "GET" ],
      "QoSOptions": {
        "ExceptionsAllowedBeforeBreaking": 3,
        "DurationOfBreak": 1000,
        "TimeoutValue": 5000
      },
      "RetryPolicy": {
        "RetryCount": 3,
        "RetryBackOff": 1000
      },
      "AuthenticationOptions": { "AuthenticationProviderKey": "Bearer" }
    },
    {
      "DownstreamPathTemplate": "/login",
      "DownstreamScheme": "https",
      "DownstreamHostAndPorts": [
        {
          "Host": "localhost",
          "Port": 7001
        }
      ],
      "UpstreamPathTemplate": "/api/login",
      "UpstreamHttpMethod": [ "POST" ],
      "QoSOptions": {
        "ExceptionsAllowedBeforeBreaking": 3,
        "DurationOfBreak": 1000,
        "TimeoutValue": 5000
      },
      "RetryPolicy": {
        "RetryCount": 3,
        "RetryBackOff": 1000
      }
    },
    {
      "DownstreamPathTemplate": "/addUser",
      "DownstreamScheme": "https",
      "DownstreamHostAndPorts": [
        {
          "Host": "localhost",
          "Port": 7001
        }
      ],
      "UpstreamPathTemplate": "/api/addUser",
      "UpstreamHttpMethod": [ "POST" ],
      "QoSOptions": {
        "ExceptionsAllowedBeforeBreaking": 3,
        "DurationOfBreak": 1000,
        "TimeoutValue": 5000
      },
      "RetryPolicy": {
        "RetryCount": 3,
        "RetryBackOff": 1000
      },
      "AuthenticationOptions": { "AuthenticationProviderKey": "Bearer" }
    },
    {
      "DownstreamPathTemplate": "/PasswordResetSendOtp",
      "DownstreamScheme": "https",
      "DownstreamHostAndPorts": [
        {
          "Host": "localhost",
          "Port": 7001
        }
      ],
      "UpstreamPathTemplate": "/api/PasswordResetSendOtp",
      "UpstreamHttpMethod": [ "POST" ],
      "QoSOptions": {
        "ExceptionsAllowedBeforeBreaking": 3,
        "DurationOfBreak": 1000,
        "TimeoutValue": 5000
      },
      "RetryPolicy": {
        "RetryCount": 3,
        "RetryBackOff": 1000
      }
    },
    {
      "DownstreamPathTemplate": "/ValidateOTP",
      "DownstreamScheme": "https",
      "DownstreamHostAndPorts": [
        {
          "Host": "localhost",
          "Port": 7001
        }
      ],
      "UpstreamPathTemplate": "/api/ValidateOTP",
      "UpstreamHttpMethod": [ "POST" ],
      "QoSOptions": {
        "ExceptionsAllowedBeforeBreaking": 3,
        "DurationOfBreak": 1000,
        "TimeoutValue": 5000
      },
      "RetryPolicy": {
        "RetryCount": 3,
        "RetryBackOff": 1000
      }
    },
    {
      "DownstreamPathTemplate": "/ResetPassword",
      "DownstreamScheme": "https",
      "DownstreamHostAndPorts": [
        {
          "Host": "localhost",
          "Port": 7001
        }
      ],
      "UpstreamPathTemplate": "/api/ResetPassword",
      "UpstreamHttpMethod": [ "POST" ],
      "QoSOptions": {
        "ExceptionsAllowedBeforeBreaking": 3,
        "DurationOfBreak": 1000,
        "TimeoutValue": 5000
      },
      "RetryPolicy": {
        "RetryCount": 3,
        "RetryBackOff": 1000
      }
    },
    {
      "DownstreamPathTemplate": "/UpdatePassword",
      "DownstreamScheme": "https",
      "DownstreamHostAndPorts": [
        {
          "Host": "localhost",
          "Port": 7001
        }
      ],
      "UpstreamPathTemplate": "/api/UpdatePassword",
      "UpstreamHttpMethod": [ "POST" ],
      "QoSOptions": {
        "ExceptionsAllowedBeforeBreaking": 3,
        "DurationOfBreak": 1000,
        "TimeoutValue": 5000
      },
      "RetryPolicy": {
        "RetryCount": 3,
        "RetryBackOff": 1000
      },
      "AuthenticationOptions": { "AuthenticationProviderKey": "Bearer" }
    },
    {
      "DownstreamPathTemplate": "/DeactivateUser",
      "DownstreamScheme": "https",
      "DownstreamHostAndPorts": [
        {
          "Host": "localhost",
          "Port": 7001
        }
      ],
      "UpstreamPathTemplate": "/api/DeactivateUser",
      "UpstreamHttpMethod": [ "POST" ],
      "QoSOptions": {
        "ExceptionsAllowedBeforeBreaking": 3,
        "DurationOfBreak": 1000,
        "TimeoutValue": 5000
      },
      "RetryPolicy": {
        "RetryCount": 3,
        "RetryBackOff": 1000
      },
      "AuthenticationOptions": { "AuthenticationProviderKey": "Bearer" }
    },
    {
      "DownstreamPathTemplate": "/ActivateUser",
      "DownstreamScheme": "https",
      "DownstreamHostAndPorts": [
        {
          "Host": "localhost",
          "Port": 7001
        }
      ],
      "UpstreamPathTemplate": "/api/ActivateUser",
      "UpstreamHttpMethod": [ "POST" ],
      "QoSOptions": {
        "ExceptionsAllowedBeforeBreaking": 3,
        "DurationOfBreak": 1000,
        "TimeoutValue": 5000
      },
      "RetryPolicy": {
        "RetryCount": 3,
        "RetryBackOff": 1000
      },
      "AuthenticationOptions": { "AuthenticationProviderKey": "Bearer" }
    },
    {
      "DownstreamPathTemplate": "/GetUserDetails/{userId}",
      "DownstreamScheme": "https",
      "DownstreamHostAndPorts": [
        {
          "Host": "localhost",
          "Port": 7001
        }
      ],
      "UpstreamPathTemplate": "/api/GetUserDetails/{userId}",
      "UpstreamHttpMethod": [ "GET" ],
      "QoSOptions": {
        "ExceptionsAllowedBeforeBreaking": 3,
        "DurationOfBreak": 1000,
        "TimeoutValue": 5000
      },
      "RetryPolicy": {
        "RetryCount": 3,
        "RetryBackOff": 1000
      },
      "AuthenticationOptions": { "AuthenticationProviderKey": "Bearer" }
    },
    {
      "DownstreamPathTemplate": "/FetchKPIData",
      "DownstreamScheme": "https",
      "DownstreamHostAndPorts": [
        {
          "Host": "localhost",
          "Port": 7001
        }
      ],
      "UpstreamPathTemplate": "/api/FetchKPIData",
      "UpstreamHttpMethod": [ "POST" ],
      "QoSOptions": {
        "ExceptionsAllowedBeforeBreaking": 3,
        "DurationOfBreak": 1000,
        "TimeoutValue": 5000
      },
      "RetryPolicy": {
        "RetryCount": 3,
        "RetryBackOff": 1000
      },
      "AuthenticationOptions": { "AuthenticationProviderKey": "Bearer" }
    },
    {
      "DownstreamPathTemplate": "/RemoveKPIforUser",
      "DownstreamScheme": "https",
      "DownstreamHostAndPorts": [
        {
          "Host": "localhost",
          "Port": 7001
        }
      ],
      "UpstreamPathTemplate": "/api/RemoveKPIforUser",
      "UpstreamHttpMethod": [ "POST" ],
      "QoSOptions": {
        "ExceptionsAllowedBeforeBreaking": 3,
        "DurationOfBreak": 1000,
        "TimeoutValue": 5000
      },
      "RetryPolicy": {
        "RetryCount": 3,
        "RetryBackOff": 1000
      },
      "AuthenticationOptions": { "AuthenticationProviderKey": "Bearer" }
    },
    {
      "DownstreamPathTemplate": "/SaveUserKPIs",
      "DownstreamScheme": "https",
      "DownstreamHostAndPorts": [
        {
          "Host": "localhost",
          "Port": 7001
        }
      ],
      "UpstreamPathTemplate": "/api/SaveUserKPIs",
      "UpstreamHttpMethod": [ "POST" ],
      "QoSOptions": {
        "ExceptionsAllowedBeforeBreaking": 3,
        "DurationOfBreak": 1000,
        "TimeoutValue": 5000
      },
      "RetryPolicy": {
        "RetryCount": 3,
        "RetryBackOff": 1000
      },
      "AuthenticationOptions": { "AuthenticationProviderKey": "Bearer" }
    },


    {
      "DownstreamPathTemplate": "/GetUniqueStatus",
      "DownstreamScheme": "https",
      "DownstreamHostAndPorts": [
        {
          "Host": "localhost",
          "Port": 7001
        }
      ],
      "UpstreamPathTemplate": "/api/GetUniqueStatus",
      "UpstreamHttpMethod": [ "GET" ],
      "QoSOptions": {
        "ExceptionsAllowedBeforeBreaking": 3,
        "DurationOfBreak": 1000,
        "TimeoutValue": 5000
      },
      "RetryPolicy": {
        "RetryCount": 3,
        "RetryBackOff": 1000
      },
      "AuthenticationOptions": { "AuthenticationProviderKey": "Bearer" }
    },

    {
      "DownstreamPathTemplate": "/GetPolicyDetail/{customerId}/{policyNumber}",
      "DownstreamScheme": "https",
      "DownstreamHostAndPorts": [
        {
          "Host": "localhost",
          "Port": 7001
        }
      ],
      "UpstreamPathTemplate": "/api/GetPolicyDetail/{customerId}/{policyNumber}",
      "UpstreamHttpMethod": [ "GET" ],
      "QoSOptions": {
        "ExceptionsAllowedBeforeBreaking": 3,
        "DurationOfBreak": 1000,
        "TimeoutValue": 5000
      },
      "RetryPolicy": {
        "RetryCount": 3,
        "RetryBackOff": 1000
      },
      "AuthenticationOptions": { "AuthenticationProviderKey": "Bearer" }
    },

    {
      "DownstreamPathTemplate": "/InvestigatorActions",
      "DownstreamScheme": "https",
      "DownstreamHostAndPorts": [
        {
          "Host": "localhost",
          "Port": 7001
        }
      ],
      "UpstreamPathTemplate": "/api/InvestigatorActions",
      "UpstreamHttpMethod": [ "GET" ],
      "QoSOptions": {
        "ExceptionsAllowedBeforeBreaking": 3,
        "DurationOfBreak": 1000,
        "TimeoutValue": 5000
      },
      "RetryPolicy": {
        "RetryCount": 3,
        "RetryBackOff": 1000
      },
      "AuthenticationOptions": { "AuthenticationProviderKey": "Bearer" }
    },

    {
      "DownstreamPathTemplate": "/getFormData/{policyNumber}",
      "DownstreamScheme": "https",
      "DownstreamHostAndPorts": [
        {
          "Host": "localhost",
          "Port": 7001
        }
      ],
      "UpstreamPathTemplate": "/api/getFormData/{policyNumber}",
      "UpstreamHttpMethod": [ "GET" ],
      "QoSOptions": {
        "ExceptionsAllowedBeforeBreaking": 3,
        "DurationOfBreak": 1000,
        "TimeoutValue": 5000
      },
      "RetryPolicy": {
        "RetryCount": 3,
        "RetryBackOff": 1000
      },
      "AuthenticationOptions": { "AuthenticationProviderKey": "Bearer" }
    },

    /* -------------------------- Missing Endpoints ----------------------------------*/


    {
      "DownstreamPathTemplate": "/send-otp",
      "DownstreamScheme": "https",
      "DownstreamHostAndPorts": [
        {
          "Host": "localhost",
          "Port": 7001
        }
      ],
      "UpstreamPathTemplate": "/api/send-otp",
      "UpstreamHttpMethod": [ "POST" ],
      "QoSOptions": {
        "ExceptionsAllowedBeforeBreaking": 3,
        "DurationOfBreak": 1000,
        "TimeoutValue": 5000
      },
      "RetryPolicy": {
        "RetryCount": 3,
        "RetryBackOff": 1000
      }
    },

    {
      "DownstreamPathTemplate": "/validate-otp",
      "DownstreamScheme": "https",
      "DownstreamHostAndPorts": [
        {
          "Host": "localhost",
          "Port": 7001
        }
      ],
      "UpstreamPathTemplate": "/api/validate-otp",
      "UpstreamHttpMethod": [ "POST" ],
      "QoSOptions": {
        "ExceptionsAllowedBeforeBreaking": 3,
        "DurationOfBreak": 1000,
        "TimeoutValue": 5000
      },
      "RetryPolicy": {
        "RetryCount": 3,
        "RetryBackOff": 1000
      }
    },

    // External API

    //{
    //  "UpstreamPathTemplate": "/twilio-handler",
    //  "UpstreamHttpMethod": [ "GET", "POST" ],
    //  "DownstreamScheme": "https",
    //  "DownstreamHostAndPorts": [
    //    {
    //      "Host": "handler.twilio.com",
    //      "Port": 443
    //    }
    //  ],
    //  "DownstreamPathTemplate": "/twiml/{{configValues:TWIML_BIN_SID}}",
    //  "QoSOptions": {
    //    "ExceptionsAllowedBeforeBreaking": 3,
    //    "DurationOfBreak": 1000,
    //    "TimeoutValue": 5000
    //  },
    //  "RetryPolicy": {
    //    "RetryCount": 3,
    //    "RetryBackOff": 1000
    //  }
    //}


  ],
  "GlobalConfiguration": {
    "RequestIdKey": "RequestId",
    "BaseUrl": "https://localhost:6001",
    "HttpHandlerOptions": {
      "UseTracing": true,
      "UseCookieContainer": true
    },
    "QoSOptions": {
      "ExceptionsAllowedBeforeBreaking": 3,
      "DurationOfBreak": 10000,
      "TimeoutValue": 5000
    },
    "RateLimitOptions": {
      "EnableRateLimiting": false
    },
    "LoadBalancerOptions": {
      "Type": "RoundRobin"
    },
    "DownstreamHttpVersion": "1.1"
  }
}